geojson_modelica_translator/__init__.py
geojson_modelica_translator/external_package_utils.py
geojson_modelica_translator/geojson/__init__.py
geojson_modelica_translator/geojson/data/schemas/building_properties.json
geojson_modelica_translator/geojson/data/schemas/district_system_properties.json
geojson_modelica_translator/geojson/data/schemas/electrical_connector_properties.json
geojson_modelica_translator/geojson/data/schemas/electrical_junction_properties.json
geojson_modelica_translator/geojson/data/schemas/region_properties.json
geojson_modelica_translator/geojson/data/schemas/site_properties.json
geojson_modelica_translator/geojson/data/schemas/thermal_connector_properties.json
geojson_modelica_translator/geojson/data/schemas/thermal_junction_properties.json
geojson_modelica_translator/geojson/schemas.py
geojson_modelica_translator/geojson/urbanopt_geojson.py
geojson_modelica_translator/geojson/urbanopt_load.py
geojson_modelica_translator/geojson_modelica_translator.py
geojson_modelica_translator/jinja_filters.py
geojson_modelica_translator/model_connectors/__init__.py
geojson_modelica_translator/model_connectors/couplings/5G_templates/Borefield_WasteHeatRecovery/ComponentDefinitions.mopt
geojson_modelica_translator/model_connectors/couplings/5G_templates/Borefield_WasteHeatRecovery/ConnectStatements.mopt
geojson_modelica_translator/model_connectors/couplings/5G_templates/GroundCoupling_Borefield/ComponentDefinitions.mopt
geojson_modelica_translator/model_connectors/couplings/5G_templates/GroundCoupling_Borefield/ConnectStatements.mopt
geojson_modelica_translator/model_connectors/couplings/5G_templates/NetworkDistributionPump_NetworkDistributionPump/ComponentDefinitions.mopt
geojson_modelica_translator/model_connectors/couplings/5G_templates/NetworkDistributionPump_NetworkDistributionPump/ConnectStatements.mopt
geojson_modelica_translator/model_connectors/couplings/5G_templates/TimeSeries_DesignDataSeries/ComponentDefinitions.mopt
geojson_modelica_translator-0.13.0.dist-info/METADATA
geojson_modelica_translator-0.13.0.dist-info/WHEEL
geojson_modelica_translator-0.13.0.dist-info/entry_points.txt
geojson_modelica_translator-0.13.0.dist-info/licenses/AUTHORS.md
geojson_modelica_translator-0.13.0.dist-info/licenses/LICENSE.md
geojson_modelica_translator-0.13.0.dist-info/RECORD
