Metadata-Version: 2.4
Name: geojson-modelica-translator
Version: 0.13.0
Summary: Package for converting GeoJSON to Modelica models for urban scale analyses.
License: BSD-4-Clause
License-File: AUTHORS.md
License-File: LICENSE.md
Keywords: URBANopt,Modelica,GeoJSON,Physics-based Modeling
Author: URBANopt DES Team
Author-email: nicholas.long@nlr.gov
Requires-Python: >=3.10,<3.14
Classifier: Development Status :: 4 - Beta
Classifier: Environment :: Console
Classifier: Intended Audience :: Developers
Classifier: Intended Audience :: Science/Research
Classifier: License :: Other/Proprietary License
Classifier: Programming Language :: Python :: 3
Classifier: Programming Language :: Python :: 3.10
Classifier: Programming Language :: Python :: 3.11
Classifier: Programming Language :: Python :: 3.12
Classifier: Programming Language :: Python :: 3.13
Classifier: Topic :: Scientific/Engineering
Requires-Dist: BuildingsPy (>=5.1,<6.0)
Requires-Dist: click (<8.2)
Requires-Dist: geojson (>=3.1,<4.0)
Requires-Dist: jinja2 (>=3.1,<4.0)
Requires-Dist: jsonpath-ng (>=1.6,<2.0)
Requires-Dist: jsonschema (>=4.20,<5.0)
Requires-Dist: modelica-builder (>=0.7.0,<0.8.0)
Requires-Dist: pandas (>=2.0,<3.0)
Requires-Dist: requests (>=2.28,<3.0)
Requires-Dist: teaser (==1.3.1)
Project-URL: Documentation, https://docs.urbanopt.net/geojson-modelica-translator/
Project-URL: Homepage, https://docs.urbanopt.net
Project-URL: Repository, https://github.com/urbanopt/geojson-modelica-translator
